bqcon/__init__.py
bqcon/query_processor.py
bqcon/sdk.py
bqcon-0.1.1.dist-info/LICENSE
bqcon-0.1.1.dist-info/METADATA
bqcon-0.1.1.dist-info/WHEEL
bqcon-0.1.1.dist-info/top_level.txt
bqcon-0.1.1.dist-info/RECORD
