Metadata-Version: 2.1
Name: bqcon
Version: 0.1.1
Summary: Python Package for doing basic operations over google big query 
Home-page: https://github.com/iyappan24/bqcon
Author: iyappan
Author-email: iyappan.akp@gmail.com
License: MIT
Keywords: big query wrapper,google big query sdk
Platform: UNKNOWN
Classifier: Programming Language :: Python :: 3
Classifier: Programming Language :: Python :: 3.5
Classifier: Programming Language :: Python :: 3.6
Classifier: Programming Language :: Python :: 3.7
Classifier: License :: OSI Approved :: MIT License
Classifier: Operating System :: OS Independent
Requires-Python: >=3.5
Requires-Dist: pandas
Requires-Dist: google-cloud
Requires-Dist: google-cloud-bigquery
Requires-Dist: pandas-gbq
